<?xml version="1.0" encoding="UTF-8" standalone="no"?>
<pk><wd nm="script&apos;" rd="440,0:1063"/><wd nm="scriptabl" rd="8,0:1772|33,0:38,100,366|441,0:406|495,0:277|666,0:517|695,0:277|860,0:104"/><wd nm="scrllock" rd="1158,0:673,824,1099"/><wd nm="scrol" rd="441,0:2511"/><wd nm="scroll" rd="441,0:2419|1158,0:575|1179,0:1327,2118,2153"/><wd nm="scrollbar" rd="1179,0:1389"/><wd nm="scrolllock" rd="1158,0:1084"/><wd nm="sdblvelocity" rd="1243,0:2028"/><wd nm="sdk" rd="8,0:3397,3462|11,0:245,285|29,0:276,316|30,0:237,277|37,0:522,562|47,0:337,377|55,0:427,486|66,0:68,176,286,411,451|67,0:51,152,160,263,374,414|71,0:261,301|1142,0:31"/><wd nm="sdkservicereleas" rd="8,0:3346|11,0:312,608|28,0:413|29,0:343,631|30,0:304,599|37,0:589,894|47,0:404,701|66,128:0,17,234,478,905,1022|67,0:441,746|71,0:328,633"/><wd nm="sdkversion" rd="8,0:3429|11,0:265,625|28,0:430|29,0:296,648|30,0:257,616|37,0:542,911|47,0:357,718|66,0:431,783|67,128:0,10,218,394,763,885,995|71,0:281,650"/><wd nm="seam" rd="158,0:4288|199,0:28|243,0:126|340,0:475|670,0:1295|784,0:500|938,0:303,345|1034,0:6962|1061,0:32,332,471,630"/><wd nm="search" rd="1,0:47,61,361,435,488,557|2,0:563|8,0:191,1059,1739,3518,3557|19,0:64,78|32,0:44|68,0:66,217|69,0:61,233|176,0:36|441,0:1955,1997,3303,3479|443,0:665|444,0:2039,2147|447,0:939,1055|628,0:401|670,0:129|671,0:255|1211,0:228,251|1226,0:489|1243,0:4612,4654"/><wd nm="searche" rd="8,0:1712|32,0:16|440,0:1570|1213,0:330|1220,0:222"/><wd nm="searchpathcount" rd="1,0:645|8,0:3472|19,0:452|68,128:0,15,146,277,530,645|69,0:293,432"/><wd nm="searchpathlist" rd="1,0:660|8,0:3528|19,0:467|68,0:316,416|69,128:0,14,141,332,547,661"/><wd nm="sec" rd="612,0:2278"/><wd nm="secant" rd="612,0:2272,2402,2636,2879"/><wd nm="second" rd="123,0:185,449|124,0:295|125,0:248,414,652|126,0:274,496,849|130,0:252,468|131,0:708|141,0:158,434|142,0:336|163,0:317,634|164,0:320,637|171,0:261,976,1042,1119,1183,1481,1547,1609,1673,1923,2263,2346,2560,2623,2727|173,0:315,866|175,0:505,709|176,0:388|180,0:427|183,0:626,850,1038|219,0:462,523,1834|227,0:446|244,0:197,517|249,0:333,972|250,0:267,675|265,0:229,518,1339|266,0:362|269,0:304|367,0:250,494|453,0:590|490,0:566,588|526,0:335,431|529,0:202|531,0:577,634,748,803,1057|538,0:822,1069|548,0:309,592|558,0:212|597,0:272,829|598,0:241,530,567|606,0:238,592|609,0:248|621,0:73,146,680|646,0:444,494|647,0:664|648,0:674|649,0:639|664,0:263,642|685,0:460,510|751,0:537|760,0:1103|835,0:179|837,0:899|845,0:184|846,0:176|847,0:168|848,0:236|850,0:373|852,0:172|872,0:4583|875,0:710|931,0:239|939,0:843|940,0:851,1852,3100|955,0:525|956,0:445|959,0:893|960,0:875|982,0:330,918|983,0:634,1892|987,0:363,1219|988,0:384,490|1016,0:399|1019,0:331,441,1181|1026,0:857,1073|1027,0:771|1037,0:560,610|1050,0:493,518,543|1063,0:351,1531|1067,0:485,535|1099,0:195|1107,0:232|1149,0:476,603|1151,0:587|1152,0:715|1155,0:388|1161,0:920|1166,0:1553|1173,0:783|1176,0:599|1183,0:702|1185,0:452|1191,0:451|1216,0:217|1218,0:184|1224,0:720|1239,0:198|1247,0:977|1251,0:1476,1491,2550|1252,0:3698|1310,0:806,1094"/><wd nm="secondarg" rd="1250,0:2941,2964"/><wd nm="section" rd="158,0:5755|227,0:66|442,0:2977|938,0:967|953,0:181,422|954,0:770,1046,1314,1811|955,0:890,1166,1595,2097|1034,0:1149|1119,0:254,277|1120,0:204,227|1121,0:243,266|1123,0:245,268,419|1124,0:195,218,369|1126,0:234,257,408|1137,0:204|1213,0:50,405,444,576,785,882,1283|1226,0:48,601,641,683,864,915,950|1243,0:3204,3219|1298,0:245|1301,0:381,565,674,732|1302,0:107|1319,0:1731"/><wd nm="section1" rd="1226,0:1592"/><wd nm="section2" rd="1226,0:1630"/><wd nm="section3" rd="1226,0:1674"/><wd nm="see" rd="0,4:141,526|1,4:158,626|2,4:690|3,4:174|4,4:502|5,4:250|6,4:1193|7,4:709|9,4:458|10,4:503|11,4:559|12,0:126|13,4:232|14,4:337,1226|15,4:318|17,4:490|18,4:270|19,4:177,436|20,4:443|21,4:858|22,4:682|23,4:529|24,4:294|25,0:228|26,4:471|27,4:232|28,4:372|29,4:590|30,4:551|32,4:413|33,0:156|35,4:601|36,4:252|37,4:836|38,4:254|39,4:538|40,4:317|41,4:704|42,4:361|43,4:250|44,4:575|45,4:306|46,4:684|47,4:651|48,4:337|49,4:407|50,4:381|51,4:694|52,4:345|53,4:380|54,4:799|55,4:766,1217|56,4:388|57,4:779|58,4:286|59,4:272|60,4:404|61,4:155|62,4:415|63,4:365|64,4:401|66,4:725|67,4:688|68,4:80,384|69,4:75,400|70,4:393|71,4:575|72,4:520|73,4:341|74,4:478|75,4:104,400|76,4:93,425|77,4:211|78,4:209|79,4:195|80,4:205|81,4:1450|82,4:538|83,4:486|84,4:491|85,4:207|86,4:532|87,4:922|89,4:530|90,4:480|91,4:249|92,4:654|93,4:359|94,4:503|95,4:420|96,4:419|97,4:416|98,4:481|99,4:830|100,4:430|101,4:388|102,4:384|103,4:541|104,4:480|105,4:742|106,4:948|107,4:544|108,4:611|109,4:360|110,4:491|111,4:883|112,4:393|113,4:519|114,4:412|115,4:688|116,4:402|117,4:530|118,4:517|119,4:533|120,4:837|121,4:1324|122,4:551|123,4:611|124,4:849|125,4:731|126,4:989|127,4:411|128,4:480|129,4:481|130,4:751|131,4:814|132,4:815|133,4:1684|134,4:1373|135,4:419|136,4:968|137,4:811|138,4:501|139,4:1188|140,4:1394|141,4:771|142,4:761|143,4:1484|144,4:680|145,4:707|146,4:689|147,4:689|148,4:82,961|149,4:609|150,4:664|151,4:594|152,4:380|153,4:611|154,4:1046|155,4:533|156,4:1017|157,4:541|158,0:5740,5788|159,4:717|160,4:782|161,4:818|162,4:764|163,4:783|164,4:788|165,4:660|166,4:736|167,4:1220|168,4:722|169,4:925|170,4:67,1184|171,4:2800|172,4:502|173,4:120,1055|174,4:490|175,4:892|176,4:914|177,4:520|178,4:861|179,4:543|180,4:953|181,4:612|182,4:700|183,4:1530|184,4:510|185,4:514|186,4:572|187,4:718|188,4:500|189,4:479|190,4:684|191,4:589|192,4:584|193,4:661|194,4:409|195,4:536|196,4:652|197,4:686|198,4:948|199,4:597|200,4:557|201,4:3167|202,4:737|203,4:661|204,4:689|205,4:1132|206,4:1385|207,4:1207|208,4:424|209,4:402|210,4:391|211,4:423|212,4:618|213,4:1059|214,4:1160|215,4:1038|216,4:892|217,4:915|220,4:169,1078|221,4:747|222,4:688|223,4:589|224,4:456|225,4:658|226,4:564|227,4:51,1061|228,4:41,609|229,4:557|230,4:578|231,4:564|232,4:593|233,4:366|234,4:536|235,4:453|236,4:491|237,4:748|238,4:559|239,4:485|240,4:657|241,4:531|242,4:631|243,4:966|244,4:577|245,4:525|246,4:834|247,4:634|248,4:1187|249,4:1511|250,4:963|251,4:1188|252,4:593|253,4:593|254,4:946|255,4:1041|256,4:89,655|257,4:713|258,4:708|259,4:375|260,4:1351|261,4:97,1080|262,4:128,1543|263,4:922|264,4:888|265,4:1400|266,4:789|267,4:484|268,4:703|269,4:739|270,4:1499|271,4:466|272,4:471|274,4:536|275,4:341|276,4:865|277,4:341|278,4:669|279,4:586|280,4:627|281,4:257|282,4:714|283,4:678|284,4:1432|285,4:550|286,4:657|287,4:689|288,4:679|289,4:619|290,4:725|291,4:627|292,4:645|293,4:538|294,4:645|295,4:771|296,4:555|297,4:604|298,4:415|299,4:415|300,4:419|301,4:524|302,4:518|303,4:594|304,4:554|305,4:348|306,4:405|307,4:422|308,4:405|309,4:479|310,4:682|311,4:531|312,4:1286|314,4:1105|315,4:622|316,4:248|317,4:248|318,4:440|319,4:422|320,4:416|321,4:319|322,4:737|323,4:306|324,4:384|325,4:402|326,4:378|328,4:433|329,4:91|330,4:238,826|331,4:200,718|332,4:126,970|333,4:133,960|334,4:151,1037|335,4:166,1056|336,4:149,995|337,4:149,995|338,4:167,1064|339,4:118,1123|340,4:121,1182|341,4:92,825|342,4:55,756|343,4:135,724|344,4:116,694|345,4:143,691,849|346,4:100,430,945|347,4:115,940|348,4:130,712|349,4:920,1162|350,4:57,1475|351,4:854|352,4:366|353,4:452|354,4:322|355,4:386|356,4:699|357,4:1955|358,4:292|359,4:449|360,4:332|361,4:1079|362,4:623|363,0:1073|364,4:589|365,4:622|366,4:930|368,4:420|369,0:155,218,280|370,4:399|371,4:135,773|372,4:138,780|373,4:135,773|374,4:387|375,4:331|376,4:371|377,4:341|378,4:365|379,4:175,858|380,4:123,911|381,4:397|382,4:473|383,4:466|384,4:1063|385,4:1065|386,4:485|387,4:586|388,4:522|389,4:533|390,4:623|391,4:562|392,4:513|393,4:682|394,4:526|395,4:768|396,4:1206|397,4:774|398,4:560|399,4:592|400,4:552|401,4:298|402,4:523|403,4:499|404,4:416|405,4:91,612|407,4:252|408,4:297|409,4:384|410,4:349|411,4:397|412,4:389|413,4:442|414,4:449|415,4:377|416,4:491|417,4:465|418,4:91,605|419,4:400|420,4:407|421,4:798|422,4:883|423,4:148,860|424,4:439|425,4:404|426,4:604|428,4:741|429,4:632|430,4:267|431,4:565|432,4:575|433,4:436|434,4:633|435,4:594|436,4:343|437,4:387|438,4:507|439,4:515|441,0:785|442,0:707|444,0:689|449,4:839|450,4:398|451,4:527|452,4:378|453,4:91,616|454,4:345|455,4:466|456,4:439|457,4:435|458,4:441|459,4:336|460,4:429|461,4:401|462,4:445|463,4:471|464,4:475|465,4:460|467,4:366|468,4:410|469,4:768|470,4:217|471,4:358|472,4:351|473,4:588|474,4:627|475,4:630|476,4:865|477,4:513|478,4:441|479,4:576|480,4:771|481,4:716|482,4:640|483,4:505|484,4:610|485,4:729|486,4:462|487,4:508|488,4:394|489,4:683|490,4:91,624|491,4:430|492,4:433|493,4:473|494,4:408|496,4:375|497,4:618|498,4:501|499,4:771|500,4:542|501,4:557|502,4:564|503,4:348|504,4:562|505,4:548|506,4:525|507,4:445|508,4:336|509,4:400|510,4:441|511,4:410|512,4:403|513,4:445|514,4:396|516,4:670|517,4:224|518,4:653|519,4:584|520,4:613|521,4:324|522,4:882|523,4:693|524,4:572|525,4:773|526,4:882|527,4:726|528,4:633|529,4:580|530,4:694|531,4:1303|532,4:762|533,4:610|534,4:533|535,4:1944|536,4:814|537,4:727|538,4:1319|539,4:666|540,4:1190|541,4:667|542,4:703|543,4:547|544,4:758|545,4:521|546,4:819|547,0:447|548,4:795|549,4:686|550,4:602|551,4:984|552,4:2020|553,4:725|554,4:670|555,4:861|556,4:831|557,4:664|558,4:541|559,4:1051|560,4:404|561,4:803|562,4:304|563,4:304|564,4:304|565,4:383|566,4:524|568,4:239|569,4:430|570,4:510|571,4:175,655|572,4:538|573,4:401|574,4:586|575,4:519|576,4:954|578,4:620|579,4:753|580,4:239|581,4:688|582,4:424|583,4:337|584,4:424|585,4:345|586,4:607|587,4:804|588,4:576|589,4:442|590,4:707|591,4:644|592,4:782|593,4:696|594,4:421|595,4:413|596,4:386|597,4:967|598,4:680|599,4:515|600,4:327|601,4:571|602,4:391|603,4:231|604,4:289|605,4:279|606,4:746|607,4:148|608,4:229|609,4:359|610,4:321|611,4:270|613,4:247|614,4:254|615,4:255|616,4:247|617,4:186|618,4:707|620,4:285|621,4:860|622,4:231|623,4:286|624,4:270|625,4:266|626,4:1437|627,4:548|628,4:1049|629,4:1193|630,4:599|631,4:447|632,4:410|633,4:849|634,4:1060|635,4:950|636,4:302|637,4:323|638,4:374|639,4:529|640,4:536|641,4:633|642,4:532|644,4:666|645,4:382|646,4:94,1765|647,4:113,767|648,4:119,779|649,4:98,737|650,4:95,578|651,4:767|652,4:1253|653,4:647|654,4:477|655,4:687|656,4:957|657,4:853|658,4:420|659,4:440|660,4:470|661,4:428|662,4:435|663,4:1226|664,4:809|665,4:881|666,4:597,1022|667,4:581|668,4:594|669,4:299,767|670,4:1702|671,4:802|672,4:1182,3196|673,4:484|674,4:402|675,4:847|676,4:298,1168|677,4:508|678,4:1035|679,4:376|680,4:1155|681,4:744|682,4:439|683,4:727|684,4:394|685,4:106,1815|686,4:680|687,4:894|688,4:89,1066|689,4:534|690,4:415|691,4:749|692,4:680|693,4:626|694,4:443|696,4:397|697,4:633|698,4:495|699,4:440|700,4:611|701,4:516|702,4:459|703,4:565|704,4:878|705,4:1061|706,4:825|708,4:382|709,4:1254|710,4:880|711,4:439|712,4:386|713,4:417|714,4:844|715,4:619|716,4:570|717,4:418|718,4:528|719,4:406|720,4:751|721,4:287,1085|722,4:1443|723,4:1237|724,4:1169|725,4:776|726,4:870|727,4:444|728,4:486|729,4:263,838|730,4:616|731,4:1558|732,4:412|733,4:454|734,4:442|735,4:314|736,4:526|737,4:517|738,4:960|739,4:811|740,4:520|741,4:565|742,4:535|743,4:489|744,4:408|745,4:376|746,4:372|747,4:384|748,4:592|749,4:418|750,4:460|751,4:1188|752,4:924|753,4:775|754,4:817|755,4:698|756,4:789|758,4:787|759,4:466|760,4:124,478,1276|761,4:974|762,4:1267|763,4:730|764,4:439|765,4:694|766,4:697|767,4:494|768,4:461|769,4:387|770,4:747|771,4:948|772,4:783|773,4:1298|774,4:1092|775,4:1578|776,4:139,1160|777,4:142,1150|778,4:160,1223|779,4:174,1241|780,4:157,1180|781,4:157,1180|782,4:175,1249|783,4:860|784,4:898|785,4:887|786,4:952|787,4:448|788,4:1039|789,4:1326|790,4:1017|791,4:1267|792,4:801|793,4:1054|794,4:534|795,4:507|796,4:782|797,4:829|798,4:1326|799,4:1365|800,4:694|801,4:719|802,4:641|803,4:768|804,4:811|805,4:849|806,4:981|807,4:1021|808,4:376|809,4:459|810,4:870|811,4:909|812,4:422|813,4:459|814,4:1192|815,4:1084|816,4:1252|817,4:1362|818,4:1036|819,4:972|820,4:1219|821,4:438|822,4:472|823,4:394|824,4:478|825,4:56,644|826,4:66,559|827,4:501|828,4:461|829,0:229,341,404|830,4:390|831,4:897,1213|832,4:703|833,4:519|834,4:995|835,4:451|836,4:323|837,4:950|838,4:304|839,4:429|840,4:622|841,4:1031|842,4:1126|843,4:80,716|844,4:468|845,4:581|846,4:438|847,4:398|848,4:472|849,4:337|850,4:610|851,4:412|852,4:347|853,4:281|854,4:393|855,4:316|856,4:416|857,4:442|858,4:391|860,0:160|865,0:341|868,0:366|870,0:624|871,0:506|872,0:1323|873,0:549|896,0:673|897,4:737|898,4:1053|899,4:673|900,4:1215|901,4:1593|902,4:2159|903,4:2050|904,4:2821|905,4:730|906,4:1244|907,4:767|908,4:679|909,4:955|910,4:668|911,4:768|912,4:697|913,4:816|914,4:1245|915,4:1087|916,4:1130|917,4:1511|918,4:1214|919,4:1086|920,4:1494|921,4:1275|922,4:1073|923,4:1161|924,4:547|925,4:737|926,4:581|928,4:263|929,4:676|930,4:751|931,4:700|932,4:399|933,4:960|934,4:93,962|935,4:981|936,4:385|937,4:203,1039|938,4:2286|939,4:2076|940,4:3209|941,4:1478|942,4:2127|943,4:1505|944,4:421|945,4:359|946,4:582|947,4:611|948,4:545|949,4:163,1145|950,4:652|951,4:350|952,4:956|953,4:147,799|954,4:142,1891|955,4:145,2178|956,4:1669|957,4:962|958,4:912|959,4:122,1036|960,4:128,1020|961,4:104,759|962,4:478|963,4:1253|964,4:80,507|965,4:88,1063|966,4:520|967,4:555|968,4:588|969,4:102,632|970,4:674|971,4:604|972,4:762|973,4:812|974,4:716|975,4:1000|976,4:459|977,4:635|978,4:435|979,4:658|980,4:1157|981,4:619|982,4:984|983,4:2062|984,4:178,874|985,4:679|986,4:875|987,4:1319|988,4:1254|989,4:327|990,4:353|991,4:581|992,4:693|993,4:725|994,4:381|995,4:392|996,4:703|997,4:553|998,4:976|999,4:643|1000,4:522|1001,4:500|1002,4:444|1003,4:409|1004,4:709|1005,4:439|1006,4:391|1007,4:571|1008,4:533|1009,4:504|1010,4:417|1011,4:562|1012,4:415|1013,4:132,470|1014,4:701|1015,4:595|1016,4:915|1017,4:817|1018,4:937|1019,4:1262|1020,4:1052|1021,4:791|1022,4:69,682|1023,4:95,800|1024,4:839|1025,4:700|1026,4:1100,1534|1027,4:97,829|1028,4:115,573|1029,4:103,1094|1030,4:134,1362|1031,4:563|1032,4:923|1033,4:687|1035,4:699|1036,4:713|1037,4:116,1883|1038,4:939|1040,4:1203|1041,4:438|1042,4:75,1485|1043,4:77,1596|1045,4:795|1046,4:667|1047,4:667|1048,4:906|1049,4:953|1050,4:1082|1051,4:516|1052,4:991|1053,4:475|1054,4:635|1055,4:645|1056,4:903|1057,4:660|1058,4:498|1059,4:814|1060,4:116,948|1061,4:70,841|1063,4:1191,2111|1065,4:594|1066,4:666|1067,4:128,1860|1068,4:756|1069,4:1412|1070,4:1057|1071,4:118,1163|1073,4:382|1074,4:443|1075,4:353|1076,4:601|1077,4:405|1078,4:485|1079,4:588|1080,4:518|1081,4:532|1082,4:592|1083,4:460|1084,4:333|1085,4:455|1086,4:484|1088,4:349|1089,4:378|1090,4:454|1091,4:476|1092,4:514|1093,4:342|1094,4:566|1095,4:1231|1096,4:318|1098,4:1056,1523|1099,4:422|1100,4:802|1101,4:441|1102,4:441|1103,4:315|1104,4:395|1105,4:570|1106,4:505|1107,4:771|1108,4:425|1109,4:1232,1698|1110,4:1099|1111,4:796|1112,4:574|1113,4:478|1114,4:804|1115,4:570|1116,4:856|1117,4:293|1118,4:472|1119,4:701|1120,4:545|1121,4:681|1122,4:301|1123,4:1037|1124,4:884|1125,4:102,541|1126,4:1017|1127,4:620|1128,4:83,1274|1129,4:620|1130,4:452|1131,4:99,425|1132,4:600|1133,4:80,671|1134,4:457|1135,4:297|1136,4:683|1137,4:525|1138,4:102,531|1139,4:663|1140,4:717|1141,4:83,1224|1143,4:482|1144,4:1138|1145,4:721|1146,4:597|1147,4:701|1148,4:822|1149,4:1135|1150,4:928|1151,4:857,1165|1152,4:1122|1153,4:436|1154,4:587|1155,4:602|1156,4:1176|1157,4:528|1158,4:325,1135|1159,4:764|1160,4:475|1161,4:1368|1162,4:528|1163,4:860|1164,4:889|1165,4:3220|1166,4:1751|1167,4:492|1168,4:609|1169,4:483|1170,4:504|1171,4:519|1172,4:813|1173,4:1237|1174,4:510|1175,4:496|1176,4:836,1071|1177,4:810|1178,4:854|1179,4:4909|1180,4:687|1181,4:667|1182,4:285|1183,4:1304|1184,4:882|1185,4:1443|1186,4:812|1187,4:921|1189,4:1110|1190,4:662|1191,4:1442|1192,4:664|1193,4:531|1195,4:681|1197,4:1011|1198,4:423|1199,4:428|1200,4:401|1201,4:401|1202,4:418|1203,4:456|1204,4:563|1205,4:522|1206,4:561|1207,4:478|1208,4:652|1209,4:793|1210,4:811|1211,4:779|1212,4:171,330,788|1213,4:1605|1214,4:170,363,730|1215,4:1116|1216,4:585|1217,4:379|1220,4:414,711|1222,4:431|1223,4:731|1224,4:1837|1225,4:866|1226,4:1699|1228,4:332|1229,4:936|1230,4:420|1231,4:567|1232,4:564|1233,4:1146|1234,4:538|1235,4:296|1236,4:403|1238,4:228|1239,4:555|1242,4:829|1244,0:602|1247,0:650|1251,0:229,1330|1252,0:389|1253,4:982|1254,4:487|1255,4:1238|1256,4:953|1257,4:733|1258,4:413|1259,4:363|1260,4:416|1261,4:669|1262,4:559|1263,4:543|1264,4:396|1265,4:540|1266,4:454|1267,4:370|1268,4:419|1269,4:497|1270,4:493|1271,4:519|1272,4:494|1273,4:348|1274,4:388|1275,4:773|1276,4:386|1277,4:337|1278,4:393|1279,4:534|1280,4:605|1281,4:65,653|1282,4:32,618|1283,4:540|1284,4:580|1285,4:446|1286,4:593|1287,4:930|1288,4:53,614|1290,4:688|1291,4:86,597|1292,4:632|1293,4:660|1294,4:1057|1295,4:620|1296,4:845|1297,4:692|1298,4:984|1299,4:431|1300,4:446|1301,4:378,1206,1933|1302,4:768|1303,4:632|1304,4:755|1305,4:614|1306,4:739|1307,4:961|1308,4:730|1309,4:485|1311,4:688|1312,4:385|1313,4:818|1314,4:657|1315,4:615|1316,4:663|1317,4:382|1318,4:465|1319,0:1716"/></pk>